{
  "queue": {
    "http://www.joseilbo.com/news/news_read.php?uid=561417&class=10&grp=": {
      "title": "법무법인 태평양, 지난해 매출 4702억 달성...전년 대비 12% 성장",
      "link": "http://www.joseilbo.com/news/news_read.php?uid=561417&class=10&grp=",
      "date": "2026-01-23 11:29",
      "press": "",
      "keyword": "포스코인터내셔널",
      "sentiment": "pos",
      "retry_count": 5,
      "last_attempt": "2026-01-23T05:20:49.422620",
      "hash_id": "754c9f7245dbdfbf"
    }
  },
  "last_updated": "2026-01-23 05:20:53",
  "count": 1
}